CHANGES.rst
COPYING
MANIFEST.in
README.rst
setup.cfg
setup.py
versioneer.py
kedifa/__init__.py
kedifa/_version.py
kedifa/app.py
kedifa/cli.py
kedifa/test.py
kedifa/updater.py
kedifa.egg-info/PKG-INFO
kedifa.egg-info/SOURCES.txt
kedifa.egg-info/dependency_links.txt
kedifa.egg-info/entry_points.txt
kedifa.egg-info/requires.txt
kedifa.egg-info/top_level.txt
kedifa.egg-info/zip-safe