Metadata-Version: 2.1
Name: kedifa
Version: 0.0.7
Summary: KEy DIstribution FAcility
Home-page: https://lab.nexedi.com/nexedi/kedifa
Author: Lukasz Nowak
Author-email: luke@nexedi.com
License: GPLv3+ with wide exception for FOSS
Keywords: key distribution ssl
Platform: UNKNOWN
Classifier: Environment :: Console
Classifier: Environment :: Web Environment
Classifier: Intended Audience :: System Administrators
Classifier: Intended Audience :: Information Technology
Classifier: License :: OSI Approved :: GNU General Public License v3 or later (GPLv3+)
Classifier: Topic :: Internet :: WWW/HTTP :: WSGI :: Application
Provides-Extra: test
License-File: COPYING
